pytest_async_benchmark/__init__.py
pytest_async_benchmark/analytics.py
pytest_async_benchmark/comparison.py
pytest_async_benchmark/display.py
pytest_async_benchmark/plugin.py
pytest_async_benchmark/runner.py
pytest_async_benchmark/stats.py
pytest_async_benchmark/utils.py
pytest_async_benchmark-0.1.1.dist-info/METADATA
pytest_async_benchmark-0.1.1.dist-info/WHEEL
pytest_async_benchmark-0.1.1.dist-info/entry_points.txt
pytest_async_benchmark-0.1.1.dist-info/licenses/LICENSE
pytest_async_benchmark-0.1.1.dist-info/RECORD
