Metadata-Version: 2.4
Name: pytest-async-benchmark
Version: 0.1.1
Summary: pytest-async-benchmark: Modern pytest benchmarking for async code. 🚀
Author-email: Mihai Farcas <contact@mihai.ltd>
License: MIT License
License-File: LICENSE
Requires-Python: >=3.9
Requires-Dist: pytest>=8.3.5
Requires-Dist: rich>=14.0.0
